{
  "kind": "singleType",
  "collectionName": "features",
  "info": {
    "name": "features",
    "description": ""
  },
  "options": {
    "increments": true,
    "timestamps": true,
    "draftAndPublish": true
  },
  "attributes": {
    "Title": {
      "type": "string",
      "required": true,
      "unique": true
    },
    "description": {
      "type": "richtext",
      "required": true
    },
    "item1": {
      "type": "string",
      "required": true,
      "unique": true
    },
    "item2": {
      "type": "string",
      "required": true,
      "unique": true
    },
    "item3": {
      "type": "string",
      "required": true,
      "unique": true
    },
    "LoginButton": {
      "type": "string",
      "required": true,
      "unique": true
    },
    "RegisterButton": {
      "type": "string",
      "required": true,
      "unique": true
    }
  }
}
